textgrid_convert/ArgParser.py
textgrid_convert/ParserABC.py
textgrid_convert/__init__.py
textgrid_convert/__main__.py
textgrid_convert/iotools.py
textgrid_convert/preproctools.py
textgrid_convert/py.typed
textgrid_convert/revParser.py
textgrid_convert/sbvParser.py
textgrid_convert/srtParser.py
textgrid_convert/textgridtools.py
textgrid_convert/ttextgrid_convert.py
textgrid_convert-1.2.0.dist-info/METADATA
textgrid_convert-1.2.0.dist-info/WHEEL
textgrid_convert-1.2.0.dist-info/entry_points.txt
textgrid_convert-1.2.0.dist-info/RECORD
