Metadata-Version: 2.4
Name: textgrid-convert
Version: 1.2.0
Summary: textgrid-convert converts audio transcripts such as sbv or srt files to Praat and DARLA compatible TextGrids
Project-URL: Homepage, https://github.com/patrickschu/textgrid-convert
Project-URL: Repository, https://github.com/patrickschu/textgrid-convert
Project-URL: Documentation, https://textgrid-convert.readthedocs.io/en/latest/
Author-email: Patrick Schultz <patrickschultz@utexas.edu>, Lars Hinrichs <lh@utexas.edu>
License: MIT
Keywords: conversion,darla,praat,textgrid,transcript
Classifier: Development Status :: 4 - Beta
Classifier: Intended Audience :: Science/Research
Classifier: Programming Language :: Python :: 3
Classifier: Programming Language :: Python :: 3.7
Classifier: Programming Language :: Python :: 3.8
Classifier: Programming Language :: Python :: 3.9
Classifier: Programming Language :: Python :: 3.10
Classifier: Programming Language :: Python :: 3.11
Classifier: Programming Language :: Python :: 3.12
Requires-Python: >=3.7
Requires-Dist: numpy
Requires-Dist: pandas
